README.md
airflow_docker_compose/__init__.py
airflow_docker_compose/__main__.py
airflow_docker_compose/airflow.cfg
airflow_docker_compose/cli.py
airflow_docker_compose/docker-compose-template.yml
airflow_docker_compose/test.py
airflow_docker_compose-0.1.9.dist-info/entry_points.txt
airflow_docker_compose-0.1.9.dist-info/LICENSE
airflow_docker_compose-0.1.9.dist-info/WHEEL
airflow_docker_compose-0.1.9.dist-info/METADATA
airflow_docker_compose-0.1.9.dist-info/RECORD
